bash_class_example/__init__.py
bash_class_example/module1.py
tests/__init__.py
tests/test_module1.py
bash_class_example-0.1.4.dist-info/LICENSE
bash_class_example-0.1.4.dist-info/METADATA
bash_class_example-0.1.4.dist-info/WHEEL
bash_class_example-0.1.4.dist-info/top_level.txt
bash_class_example-0.1.4.dist-info/RECORD
