Metadata-Version: 2.1
Name: bash_class_example
Version: 0.1.4
Summary: A test of Classes stored in Bash Class
Home-page: https://github.com/stbbash/bash_class_example.git
Author: Donatus Ajaezu
Author-email: donatusajaezu@example.com
Classifier: Programming Language :: Python :: 3
Classifier: License :: OSI Approved :: MIT License
Classifier: Operating System :: OS Independent
Requires-Python: >=3.6
License-File: LICENSE
